blank_template-0.0.9.dist-info/METADATA
blank_template-0.0.9.dist-info/WHEEL
blank_template-0.0.9.dist-info/entry_points.txt
blank_template-0.0.9.dist-info/licenses/LICENSE
blank_template/__init__.py
blank_template/__main__.py
blank_template-0.0.9.dist-info/RECORD
